{
  "generator-jhipster": {
    "applicationIndex": 2,
    "applicationType": "microservice",
    "authenticationType": "oauth2",
    "baseName": "store",
    "blueprints": [
      {
        "name": "generator-jhipster-cassandra-composite-primary-key",
        "version": "1.0.1"
      }
    ],
    "buildTool": "maven",
    "clientFramework": "angular",
    "databaseType": "cassandra",
    "devDatabaseType": "cassandra",
    "devServerPort": 4202,
    "enableHibernateCache": false,
    "entities": ["Product"],
    "jhipsterVersion": "8.6.0",
    "jwtSecretKey": "YTFmYmIwZDQ4ZjNmMTgwMGNmZjUyYzM3NzJmMzEwNTk4NGI4ZjczODJkMWRhNjhlMWU3OWNkZTVjMDk0ZWI4ODBiMDgzMTE5OGU0ZGYyMWVjMTViNjcxYzY1YWYyZjQ0ZjVmOTI0ZTM1NTA0NWQwNjZhNjQyZWZhMDE3NTE1Nzk=",
    "languages": ["en"],
    "lastLiquibaseTimestamp": 1721155640000,
    "monorepository": true,
    "nativeLanguage": "en",
    "packageFolder": "com/saathratri/developer/store",
    "packageName": "com.saathratri.developer.store",
    "prodDatabaseType": "cassandra",
    "serverPort": "8082",
    "serviceDiscoveryType": "eureka",
    "skipCommitHook": true,
    "skipJhipsterDependencies": true,
    "skipUserManagement": true,
    "testFrameworks": ["cypress"]
  }
}
